toadr3/__init__.py
toadr3/_internal/__init__.py
toadr3/_internal/client_name.py
toadr3/_internal/object_id.py
toadr3/_internal/objects.py
toadr3/_internal/parameter_builder.py
toadr3/_internal/query_handler.py
toadr3/_internal/query_parameter.py
toadr3/_internal/skip_and_limit.py
toadr3/_internal/targets.py
toadr3/access_token.py
toadr3/client.py
toadr3/events.py
toadr3/exceptions.py
toadr3/models/__init__.py
toadr3/models/docstringbasemodel.py
toadr3/models/event.py
toadr3/models/eventpayloaddescriptor.py
toadr3/models/interval.py
toadr3/models/intervalperiod.py
toadr3/models/isoduration.py
toadr3/models/objectoperation.py
toadr3/models/problem.py
toadr3/models/program.py
toadr3/models/report.py
toadr3/models/reportdata.py
toadr3/models/reportdescriptor.py
toadr3/models/reportpayloaddescriptor.py
toadr3/models/subscription.py
toadr3/models/targettype.py
toadr3/models/valuesmap.py
toadr3/programs.py
toadr3/py.typed
toadr3/reports.py
toadr3/subscriptions.py
toadr3-0.28.0.dist-info/METADATA
toadr3-0.28.0.dist-info/WHEEL
toadr3-0.28.0.dist-info/licenses/LICENSE
toadr3-0.28.0.dist-info/RECORD
