Metadata-Version: 2.4
Name: toadr3
Version: 0.28.0
Summary: Tiny OpenADR 3 compatible client Python Library
License: Apache-2.0
License-File: LICENSE
Author: Jean-Paul Balabanian
Author-email: jean-paul.balabanian@eviny.no
Requires-Python: >=3.11,<4.0
Classifier: License :: OSI Approved :: Apache Software License
Classifier: Programming Language :: Python :: 3
Classifier: Programming Language :: Python :: 3.11
Classifier: Programming Language :: Python :: 3.12
Classifier: Programming Language :: Python :: 3.13
Classifier: Programming Language :: Python :: 3.14
Requires-Dist: aiodns (>=3.2.0,<4.0.0)
Requires-Dist: aiohttp (>=3.10.5,<4.0.0)
Requires-Dist: pydantic (>=2.11.1,<3.0.0)
Project-URL: Repository, https://github.com/prelectai/toadr3
